Offuscat/Offuscats.py
Offuscats-1.0.1.dist-info/METADATA
Offuscats-1.0.1.dist-info/WHEEL
Offuscats-1.0.1.dist-info/top_level.txt
Offuscats-1.0.1.dist-info/RECORD
