Metadata-Version: 2.1
Name: Offuscats
Version: 1.0.1
Summary: A Python obfuscator. Github official : https://github.com/TryWarzFiles/Offuscat
Home-page: https://github.com/TryWarzFiles/Offuscat
Author: TryWarz
Author-email: trywarz@trywarz.online
License: apache-2.0
Keywords: obfuscation,obfuscate,obfuscator,obfuscating,obfuscated,obfuscates,obfuscators
Platform: UNKNOWN
